pygenpass/__init__.py
pygenpass/database.py
pygenpass/password.py
pygenpass-0.2.dist-info/LICENSE
pygenpass-0.2.dist-info/METADATA
pygenpass-0.2.dist-info/WHEEL
pygenpass-0.2.dist-info/entry_points.txt
pygenpass-0.2.dist-info/top_level.txt
pygenpass-0.2.dist-info/RECORD
