Metadata-Version: 2.1
Name: pygenpass
Version: 0.2
Summary: Pygenpass - Command Line Password Generator and Manager Tool
Home-page: https://github.com/paint-it/pygenpass
Author: Mayuri Lahane
Author-email: mayurilahane1998@gmail.com
License: MIT License
Keywords: clitool,passwordmanager
Platform: UNKNOWN
Classifier: Development Status :: 4 - Beta
Classifier: Programming Language :: Python
Classifier: Programming Language :: Python :: 3.6
Classifier: Programming Language :: Python :: 3.7
Classifier: Environment :: Console
Classifier: Topic :: Internet
Classifier: Topic :: Utilities
Requires-Python: >=3.6
Requires-Dist: beautifultable
Requires-Dist: click
Requires-Dist: diceware
